jmllib/__init__.py
jmllib/expr.py
jmllib/jml.py
jmllib-0.1.2.dist-info/LICENSE
jmllib-0.1.2.dist-info/METADATA
jmllib-0.1.2.dist-info/WHEEL
jmllib-0.1.2.dist-info/top_level.txt
jmllib-0.1.2.dist-info/RECORD
