Metadata-Version: 2.1
Name: jmllib
Version: 0.1.2
Summary: jolly markup language
License: Apache License
Project-URL: Homepage, https://github.com/DanDanCool/jml
Requires-Python: >=3.10
License-File: LICENSE
